tilakone/__init__.py
tilakone/tilakone.py
tilakone-0.1.0.dist-info/METADATA
tilakone-0.1.0.dist-info/WHEEL
tilakone-0.1.0.dist-info/RECORD
