Metadata-Version: 2.1
Name: tilakone
Version: 0.1.0
Summary: Super simple state machine
Author: Panu Oksiala
Author-email: panu@oksiala.fi
Requires-Python: >=3.11,<4.0
Classifier: Programming Language :: Python :: 3
Classifier: Programming Language :: Python :: 3.11
Classifier: Programming Language :: Python :: 3.12
